foldora/__init__.py
foldora/__main__.py
foldora/commands.py
foldora/utils.py
foldora-0.0.6.dist-info/licenses/LICENCE
foldora-0.0.6.dist-info/METADATA
foldora-0.0.6.dist-info/WHEEL
foldora-0.0.6.dist-info/entry_points.txt
foldora-0.0.6.dist-info/top_level.txt
foldora-0.0.6.dist-info/RECORD
