Metadata-Version: 2.4
Name: foldora
Version: 0.0.6
Summary: A CLI tool that manages files and directories.
Author: Ayoub A.
Author-email: aberbach.me@gmail.com
Maintainer: Ayoub A.
Maintainer-email: aberbach.me@gmail.com
License: MIT
Project-URL: Homepage, https://pypi.org/project/foldora/
Project-URL: Repository, https://github.com/old-ghost/foldora
Project-URL: Issues, https://github.com/old-ghost/foldora/issues
Project-URL: Changelog, https://github.com/old-ghost/foldora/releases
Keywords: cli,file i/o,file/directory manager
Classifier: Intended Audience :: Developers
Classifier: Development Status :: 3 - Alpha
Classifier: Programming Language :: Python :: 3
Classifier: License :: OSI Approved :: MIT License
Requires-Python: >=3.6
License-File: LICENCE
Requires-Dist: click
Requires-Dist: colorama
Requires-Dist: importlib-metadata; python_version < "3.12"
Dynamic: license-file
